certbot_dns_stackit/__init__.py
certbot_dns_stackit/stackit.py
certbot_dns_stackit/test_stackit.py
certbot_dns_stackit-0.1.3.dist-info/licenses/LICENSE
certbot_dns_stackit-0.1.3.dist-info/METADATA
certbot_dns_stackit-0.1.3.dist-info/WHEEL
certbot_dns_stackit-0.1.3.dist-info/entry_points.txt
certbot_dns_stackit-0.1.3.dist-info/top_level.txt
certbot_dns_stackit-0.1.3.dist-info/RECORD
