Metadata-Version: 2.4
Name: certbot-dns-stackit
Version: 0.1.3
Summary: STACKIT DNS Authenticator plugin for Certbot
Home-page: https://github.com/stackitcloud/certbot-dns-stackit
Author: STACKIT DNS
Author-email: dns@stackit.cloud
License: Apache License 2.0
Classifier: Development Status :: 5 - Production/Stable
Classifier: Environment :: Plugins
Classifier: Intended Audience :: System Administrators
Classifier: License :: OSI Approved :: Apache Software License
Classifier: Operating System :: POSIX :: Linux
Classifier: Programming Language :: Python
Classifier: Programming Language :: Python :: 3
Classifier: Programming Language :: Python :: 3.4
Classifier: Programming Language :: Python :: 3.5
Classifier: Programming Language :: Python :: 3.6
Classifier: Programming Language :: Python :: 3.7
Classifier: Programming Language :: Python :: 3.8
Classifier: Programming Language :: Python :: 3.9
Classifier: Programming Language :: Python :: 3.10
Classifier: Programming Language :: Python :: 3.11
Classifier: Topic :: Internet :: WWW/HTTP
Classifier: Topic :: Security
Classifier: Topic :: System :: Installation/Setup
Classifier: Topic :: System :: Networking
Classifier: Topic :: System :: Systems Administration
Classifier: Topic :: Utilities
Requires-Python: >=2.7, !=3.0.*, !=3.1.*, !=3.2.*, !=3.3.*
License-File: LICENSE
Requires-Dist: acme>=2.6.0
Requires-Dist: certbot>=2.6.0
Requires-Dist: setuptools
Requires-Dist: requests
Requires-Dist: mock
Requires-Dist: requests-mock
Requires-Dist: mypy
Requires-Dist: mypy-extensions
Requires-Dist: types-requests
Requires-Dist: types-urllib3
Requires-Dist: flake8
Requires-Dist: pydocstyle
Requires-Dist: black
Requires-Dist: click==8.2.1
Requires-Dist: coverage
Requires-Dist: PyJWT==2.10.1
Dynamic: author
Dynamic: author-email
Dynamic: classifier
Dynamic: description
Dynamic: description-content-type
Dynamic: home-page
Dynamic: license
Dynamic: license-file
Dynamic: requires-dist
Dynamic: requires-python
Dynamic: summary
